reescritor
