Metadata-Version: 2.1
Name: reescritor
Version: 0.0.4
Summary: A Python module for Spanish Spinner (Reescritor.com & DisparaTusIngresos.com)
Home-page: https://github.com/nicolasmarin/reescritor
Author: nicolasmarin
Author-email: info@scraping.link
License: GPLv3
Download-URL: https://github.com/nicolasmarin/reescritor/archive/refs/heads/main.zip
Keywords: spinner,spanish,spintax
Platform: UNKNOWN
Classifier: Programming Language :: Python :: 3
Classifier: Operating System :: OS Independent
Classifier: Topic :: Software Development :: Build Tools
Classifier: License :: OSI Approved :: GNU General Public License v3 (GPLv3)
